fisheries/__init__.py
fisheries/cli.py
fisheries/fisheries.py
fisheries-0.1.0.dist-info/AUTHORS.rst
fisheries-0.1.0.dist-info/LICENSE
fisheries-0.1.0.dist-info/METADATA
fisheries-0.1.0.dist-info/WHEEL
fisheries-0.1.0.dist-info/entry_points.txt
fisheries-0.1.0.dist-info/top_level.txt
fisheries-0.1.0.dist-info/RECORD
