Metadata-Version: 2.1
Name: fisheries
Version: 0.1.0
Summary: OpenFisheries Python package
Home-page: https://github.com/isedwards/fisheries
Author: Ian Edwards
Author-email: ian@myacorn.com
License: MIT license
Keywords: fisheries
Platform: UNKNOWN
Classifier: Development Status :: 2 - Pre-Alpha
Classifier: Intended Audience :: Developers
Classifier: License :: OSI Approved :: MIT License
Classifier: Natural Language :: English
Classifier: Programming Language :: Python :: 3
Classifier: Programming Language :: Python :: 3.6
Classifier: Programming Language :: Python :: 3.7
Classifier: Programming Language :: Python :: 3.8
Requires-Python: >=3.6
License-File: LICENSE
License-File: AUTHORS.rst
Requires-Dist: Click (>=7.0)
